queryset_reporter/__init__.py
queryset_reporter/admin.py
queryset_reporter/apps.py
queryset_reporter/core.py
queryset_reporter/forms.py
queryset_reporter/introspect.py
queryset_reporter/mapping.py
queryset_reporter/models.py
queryset_reporter/settings.py
queryset_reporter/tests.py
queryset_reporter/urls.py
queryset_reporter/management/__init__.py
queryset_reporter/management/commands/__init__.py
queryset_reporter/management/commands/automatic_generation.py
queryset_reporter/management/commands/purge.py
queryset_reporter/migrations/0001_initial.py
queryset_reporter/migrations/0002_auto_20191003_0105.py
queryset_reporter/migrations/0003_auto_20191029_1842.py
queryset_reporter/migrations/0004_auto_20200330_2152.py
queryset_reporter/migrations/__init__.py
queryset_reporter/static/bootstrap/css/bootstrap-2.2.1-datepicker.css
queryset_reporter/static/bootstrap/css/bootstrap-2.2.1.css
queryset_reporter/static/bootstrap/img/glyphicons-halflings-white.png
queryset_reporter/static/bootstrap/img/glyphicons-halflings.png
queryset_reporter/static/bootstrap/js/bootstrap-2.2.1-datepicker.js
queryset_reporter/static/bootstrap/js/bootstrap-2.2.1.js
queryset_reporter/static/bootstrap/js/jquery-1.8.3.min.js
queryset_reporter/static/queryset_reporter/admin.css
queryset_reporter/static/queryset_reporter/admin.js
queryset_reporter/static/queryset_reporter/queryset_reporter.css
queryset_reporter/static/queryset_reporter/reporter.js
queryset_reporter/templates/admin/queryset_reporter_change_form.html
queryset_reporter/templates/queryset_reporter/base.html
queryset_reporter/templates/queryset_reporter/create.html
queryset_reporter/templates/queryset_reporter/filter_fields.html
queryset_reporter/templatetags/__init__.py
queryset_reporter/templatetags/dict_utils.py
queryset_reporter/views/__init__.py
queryset_reporter/views/ajax.py
queryset_reporter/views/core.py
queryset_reporter-2.2.0.dist-info/LICENSE
queryset_reporter-2.2.0.dist-info/METADATA
queryset_reporter-2.2.0.dist-info/WHEEL
queryset_reporter-2.2.0.dist-info/top_level.txt
queryset_reporter-2.2.0.dist-info/RECORD
